botnetics/__init__.py
botnetics/app.py
botnetics/cli.py
botnetics/models.py
botnetics/urls.py
botnetics/views.py
botnetics_agent-0.1.8.dist-info/licenses/LICENSE
botnetics_agent-0.1.8.dist-info/METADATA
botnetics_agent-0.1.8.dist-info/WHEEL
botnetics_agent-0.1.8.dist-info/entry_points.txt
botnetics_agent-0.1.8.dist-info/top_level.txt
botnetics_agent-0.1.8.dist-info/RECORD
